LICENSE
README.md
pyproject.toml
setup.py
src/tensorloader/__init__.py
src/tensorloader/_loader.py
src/tensorloader.egg-info/PKG-INFO
src/tensorloader.egg-info/SOURCES.txt
src/tensorloader.egg-info/dependency_links.txt
src/tensorloader.egg-info/top_level.txt