Metadata-Version: 2.1
Name: tensorloader
Version: 0.1.0
Summary: A faster dataloader for tensor data.
Author-email: ZHB <zhb2000@zju.edu.cn>
License: Apache-2.0
Project-URL: Source, https://github.com/zhb2000/tensorloader
Project-URL: Bug Tracker, https://github.com/zhb2000/tensorloader/issues
Keywords: pytorch
Classifier: Programming Language :: Python :: 3
Classifier: Programming Language :: Python :: 3.8
Classifier: Programming Language :: Python :: 3.9
Classifier: Programming Language :: Python :: 3.10
Classifier: License :: OSI Approved :: Apache Software License
Classifier: Operating System :: OS Independent
Classifier: Topic :: Scientific/Engineering :: Artificial Intelligence
Classifier: Typing :: Typed
Requires-Python: >=3.8
License-File: LICENSE
